{
    "Q642878": "Marvel Cinematic Universe",
    "Q31202708": "Top Gun: Maverick",
    "Q89474225": "The Marvels",
    "Q3604746": "Avatar: The Way of Water",
    "Q54860489": "Black Panther: Wakanda Forever",
    "Q68934496": "Spider-Man: No Way Home",
    "Q64211112": "Doctor Strange in the Multiverse of Madness",
    "Q61117344": "The Batman",
    "Q65768604": "Thor: Love and Thunder",
    "Q55178974": "Jurassic World Dominion",
    "Q23781155": "Avengers: Endgame",
    "Q110138": "Top Gun",
    "Q23894629": "Eternals",
    "Q27985819": "Spider-Man: Far from Home",
    "Q21534241": "No Time to Die",
    "Q61633664": "The King's Man",
    "Q99900595": "Bullet Train",
    "Q29226331": "Guardians of the Galaxy Vol. 3"
}