{
    "Q444698": "Operation Paperclip",
    "Q46857": "scientific method",
    "Q336": "science",
    "Q34358": "The Doctor",
    "Q762": "Leonardo da Vinci",
    "Q58978": "Max Born",
    "Q2602422": "Egon Spengler",
    "Q79037": "Spider-Man",
    "Q33085422": "Thirteenth Doctor",
    "Q139890": "Zack Snyder",
    "Q307": "Galileo Galilei",
    "Q150827": "Frankenstein; or, The Modern Prometheus",
    "Q6694": "Alexander von Humboldt",
    "Q7604": "Leonhard Euler",
    "Q156379": "Yury Luzhkov",
    "Q58720": "Mikhail Vassilyevich Lomonosov",
    "Q439693": "Lionel Logue",
    "Q170842": "Sergei Korolev",
    "Q61585334": "Valentina Tazekenova"
}